[
    {
       
        "areas": [
            {
                "area": "Identifying and seizing opportunities to create value by exploring the social, cultural and economic landscape"
            },
            {
                "area": "Identifying needs and challenges that need to be met"
                  
            },
            {
                "area": "Establishing new connections and bring together scattered elements of the landscape to create opportunities to create value"
               
            },
            {
                "area": "Developing several ideas and opportunities to create value, including better solutions to existing and new challenges"
                
            },
            {
                "area": "Combining knowledge and resources to achieve valuable effects"
                
            },
            {
                "area": "Imagining the future"
                
            },
            {
                "area": "Developing a vision to turn ideas into action"
                
            },
            {
                "area": "Visualizing future scenarios to help guide effort and action"
                
            },

            {
                "area": "Judging what value is in social, cultural and economic terms"
            },
            {
                "area": "Recognizing the potential an idea has for creating value and identify suitable ways of making the most out of it"
            },
            {
                "area": "Assessing the consequences of ideas that bring value"
            },
            {
                "area": "Assessing the effect of entrepreneurial action on the target community, the market, society and the environment"
            },
            {
                "area": "Reflecting on how sustainable long-term social, cultural and economic goals are"
            },
            {
                "area": "Reflecting on how sustainable the course of action chosen is"
            },
            {
                "area": "Self-awareness & self-efficacy"
            },
            {
                "area": "Believing in yourself"
            }, 
            {
                "area": "Continious personal development"
            }, 
            {
                "area": "Reflecting on your needs, aspirations and wants in the short, medium and long term"
            }, 
            {
                "area": "Identifying and assessing your individual strengths and weaknesses"
            }, 
            {
                "area": "Identifying and assessing my team's strenghts and weaknesses"
            }, 
            {
                "area": "Believing in your ability to influence others"
            }, 
            {
                "area": "Being determined to turn ideas into action"
            }, 
            {
                "area": "Satisfying your needs to achieve"
            }, 
            {
                "area": "Being prepared to be patient to reach your goals"
            }, 
            {
                "area": "Trying to achieve your long-term individual or group aims"
            }, 
            {
                "area": "I display resilience under pressure, adversity, and temporary failure"
            }, 
            {
                "area": "Obtaining resources needed to turn ideas into action"
            }, 
            {
                "area": "Manage resources needed to turn into action"
            }, 
            {
                "area": "Making the most of limited resources"
            }, 
            {
                "area": "Obtaining relevant competences needed at different stages of starting and running your own venture including technical, legal, tax and digital competences"
            }, 
            {
                "area": "Estimating the cost of turning an idea into a value-creating activity"
            }, 
            {
                "area": "Planning, putting in place and evaluating financial decisions over time"
            }, 
            {
                "area": "Managing internal finances to make sure your value-creating activity can last over the long term"
            }, 
            {
                "area": "Dealing with external funding requirements to make sure your opportunity can last over the long run"
            }, 
            {
                "area": "Inspiring and enthusing relevant stakeholders"
            }, 
            {
                "area": "Getting the support needed to achieve valuable outcomes"
            }, 
            {
                "area": "Demonstrating effective communication"
            }, 
            {
                "area": "Demonstrating effective persuasion skills"
            }, 
            {
                "area": "Negotiating effectively and leadership"
            }, 
            {
                "area": "Showing leadership"
            }, 
            {
                "area": "Initiating processes that create value"
            }, 
            {
                "area": "Taking up challenges"
            }, 
            {
                "area": "Acting and working independently to achieve goals"
            }, 
            {
                "area": "Sticking to intentions and carrying out planned tasks"
            }, 
            {
                "area": "Setting long-, medium- and short-term goals"
            }, 
            {
                "area": "Defining priorities and action plans"
            }, 
            {
                "area": "Adapting to unforeseen changes"
            }, 
            {
                "area": "Making decisions based on partial or ambiguous information"
            }, 
            {
                "area": "Making decisions in the face of uncertain outcomes or when there is a risk of unintended outcomes"
            }, 
            {
                "area": "Testing ideas and prototypes from the early stages, to reduce risks of failing"
            }, 
            {
                "area": "Handling fast-moving situations promptly and flexibly"
            }, 
            {
                "area": "Working together and co-operating with others to develop ideas and turn them into action"
            }, 
            {
                "area": "Networking"
            }, 
            {
                "area": "Solving conflicts"
            }, 
            {
                "area": "Facing up to competition with a positive mindset when necessary"
            }, 
            {
                "area": "Using any initiative for value creation as a learning opportunity"
            }, 
            {
                "area": "Learning with others, including peers and mentors"
            }, 
            {
                "area": "Reflecting and learning from both success and failure (you own and other people's)"
            }
        ]
    }
]